spotme/spotme.py
spotme-1.2.0.dist-info/DESCRIPTION.rst
spotme-1.2.0.dist-info/METADATA
spotme-1.2.0.dist-info/RECORD
spotme-1.2.0.dist-info/WHEEL
spotme-1.2.0.dist-info/entry_points.txt
spotme-1.2.0.dist-info/metadata.json
spotme-1.2.0.dist-info/top_level.txt
