Metadata-Version: 2.0
Name: spotme
Version: 1.2.0
Summary: A command line tool that allows you to spin up AWS EC2 Spot Instances instantly
Home-page: https://github.com/joeyism/py-spotme
Author: Joey Sham
Author-email: sham.joey@gmail.com
License: UNKNOWN
Platform: UNKNOWN
Requires-Dist: boto3
Requires-Dist: click
Requires-Dist: terminaltables
Requires-Dist: dfault
